[
  {
    "full_name": "cloudposse/github-action-atmos-affected-trigger-spacelift",
    "stargazers_count": 1,
    "open_issues_count": 0,
    "forks_count": 0
  },
  {
    "full_name": "imdario/mergo",
    "stargazers_count": 2400,
    "open_issues_count": 33,
    "forks_count": 254
  },
  {
    "full_name": "cloudposse/github-action-terraform-plan-storage",
    "stargazers_count": 3,
    "open_issues_count": 4,
    "forks_count": 1
  },
  {
    "full_name": "cloudposse/github-action-setup-atmos",
    "stargazers_count": 5,
    "open_issues_count": 13,
    "forks_count": 1
  },
  {
    "full_name": "cloudposse/terratest-helpers",
    "stargazers_count": 1,
    "open_issues_count": 1,
    "forks_count": 0
  },
  {
    "full_name": "1debit/alternat",
    "stargazers_count": 670,
    "open_issues_count": 4,
    "forks_count": 35
  },
  {
    "full_name": "cloudposse/atmos",
    "stargazers_count": 392,
    "open_issues_count": 47,
    "forks_count": 66
  },
  {
    "full_name": "rebuy-de/aws-nuke",
    "stargazers_count": 4510,
    "open_issues_count": 195,
    "forks_count": 619
  },
  {
    "full_name": "gruntwork-io/terragrunt",
    "stargazers_count": 6808,
    "open_issues_count": 596,
    "forks_count": 869
  },
  {
    "full_name": "cloudposse/github-action-terratest",
    "stargazers_count": 10,
    "open_issues_count": 5,
    "forks_count": 1
  },
  {
    "full_name": "Noovolari/leapp",
    "stargazers_count": 1379,
    "open_issues_count": 91,
    "forks_count": 105
  },
  {
    "full_name": "cloudposse/lambda-github-action-token-rotator",
    "stargazers_count": 2,
    "open_issues_count": 11,
    "forks_count": 0
  },
  {
    "full_name": "awslabs/aws-lambda-powertools-typescript",
    "stargazers_count": 1169,
    "open_issues_count": 57,
    "forks_count": 91
  },
  {
    "full_name": "DataDog/agent-github-action",
    "stargazers_count": 10,
    "open_issues_count": 4,
    "forks_count": 9
  },
  {
    "full_name": "cloudposse/terraform-aws-lambda-function",
    "stargazers_count": 17,
    "open_issues_count": 11,
    "forks_count": 32
  },
  {
    "full_name": "gruntwork-io/git-xargs",
    "stargazers_count": 792,
    "open_issues_count": 35,
    "forks_count": 44
  },
  {
    "full_name": "cloudposse/terraform-aws-ecr-public",
    "stargazers_count": 6,
    "open_issues_count": 0,
    "forks_count": 2
  },
  {
    "full_name": "backstage/backstage",
    "stargazers_count": 22007,
    "open_issues_count": 437,
    "forks_count": 4093
  },
  {
    "full_name": "cloudposse/terraform-aws-api-gateway",
    "stargazers_count": 16,
    "open_issues_count": 6,
    "forks_count": 16
  },
  {
    "full_name": "aws/aws-proton-public-roadmap",
    "stargazers_count": 194,
    "open_issues_count": 40,
    "forks_count": 12
  },
  {
    "full_name": "remoteintech/remote-jobs",
    "stargazers_count": 24613,
    "open_issues_count": 48,
    "forks_count": 2619
  },
  {
    "full_name": "knative/serving",
    "stargazers_count": 4996,
    "open_issues_count": 188,
    "forks_count": 1031
  },
  {
    "full_name": "hashicorp/terraform-exec",
    "stargazers_count": 524,
    "open_issues_count": 64,
    "forks_count": 90
  },
  {
    "full_name": "mathieudutour/timezone-butler",
    "stargazers_count": 122,
    "open_issues_count": 29,
    "forks_count": 16
  },
  {
    "full_name": "AcalephStorage/awesome-devops",
    "stargazers_count": 1009,
    "open_issues_count": 9,
    "forks_count": 140
  },
  {
    "full_name": "dzharii/awesome-typescript",
    "stargazers_count": 3885,
    "open_issues_count": 0,
    "forks_count": 355
  },
  {
    "full_name": "enaqx/awesome-react",
    "stargazers_count": 55717,
    "open_issues_count": 4,
    "forks_count": 6724
  },
  {
    "full_name": "expressjs/express",
    "stargazers_count": 60935,
    "open_issues_count": 171,
    "forks_count": 10472
  },
  {
    "full_name": "LappleApple/awesome-leading-and-managing",
    "stargazers_count": 6923,
    "open_issues_count": 2,
    "forks_count": 591
  },
  {
    "full_name": "VladRassokhin/intellij-hcl",
    "stargazers_count": 245,
    "open_issues_count": 103,
    "forks_count": 48
  }
]